[
  {
    "track": {
      "asset": "BTCUSDT",
      "timeframe": "1d",
      "venue": "spot",
      "mode": "long_only"
    },
    "ok": true,
    "as_of": "2026-06-12T23:59:59.999000+00:00",
    "current_close": 63474.0,
    "current_bar_high": 63863.98,
    "current_bar_low": 63301.53,
    "current_atr_24h": 1480.1455633702317,
    "selected_strategy": "meanrev",
    "selected_params": {
      "window_h": 168,
      "entry_z": 2.5,
      "exit_z": 0.5
    },
    "param_label": "w168h_z2.5_x0.5",
    "train_sharpe": -0.755112505322233,
    "train_n_trades": 3,
    "train_in_market_pct": 0.8442622950819673,
    "stand_down": true,
    "raw_strategy_signal": 0,
    "current_signal": 0,
    "prior_signal": 0,
    "is_flip": false,
    "target_units": 0.0,
    "target_notional_sgd": 0.0,
    "stop_price": null,
    "stop_distance_pct": 9.327570743108875,
    "prior_recommended_signal": 0,
    "first_run": false,
    "asset_realized_vol_60d": 0.38400244502132647,
    "weight": 0.2206650232294012,
    "allocated_nav": 220.6650232294012
  },
  {
    "track": {
      "asset": "ETHUSDT",
      "timeframe": "1d",
      "venue": "spot",
      "mode": "long_only"
    },
    "ok": true,
    "as_of": "2026-06-12T23:59:59.999000+00:00",
    "current_close": 1668.81,
    "current_bar_high": 1682.0,
    "current_bar_low": 1660.93,
    "current_atr_24h": 48.511907561750675,
    "selected_strategy": "tsmom",
    "selected_params": {
      "lookback_h": 168
    },
    "param_label": "lb168h",
    "train_sharpe": -0.15315889044809677,
    "train_n_trades": 3,
    "train_in_market_pct": 0.912568306010929,
    "stand_down": true,
    "raw_strategy_signal": 1,
    "current_signal": 0,
    "prior_signal": 0,
    "is_flip": false,
    "target_units": 0.0,
    "target_notional_sgd": 0.0,
    "stop_price": null,
    "stop_distance_pct": 5.813952164925986,
    "prior_recommended_signal": 0,
    "first_run": false,
    "asset_realized_vol_60d": 0.5265800680104353,
    "weight": 0.16091742471554893,
    "allocated_nav": 160.91742471554892
  },
  {
    "track": {
      "asset": "SOLUSDT",
      "timeframe": "1d",
      "venue": "spot",
      "mode": "long_only"
    },
    "ok": true,
    "as_of": "2026-06-12T23:59:59.999000+00:00",
    "current_close": 66.81,
    "current_bar_high": 67.3,
    "current_bar_low": 66.42,
    "current_atr_24h": 2.4520774730315784,
    "selected_strategy": "macross",
    "selected_params": {
      "fast_h": 168,
      "slow_h": 720
    },
    "param_label": "f168h_s720h",
    "train_sharpe": -0.4088409350579963,
    "train_n_trades": 3,
    "train_in_market_pct": 0.6038251366120219,
    "stand_down": true,
    "raw_strategy_signal": 0,
    "current_signal": 0,
    "prior_signal": 0,
    "is_flip": false,
    "target_units": 0.0,
    "target_notional_sgd": 0.0,
    "stop_price": null,
    "stop_distance_pct": 7.340450450625889,
    "prior_recommended_signal": 0,
    "first_run": false,
    "asset_realized_vol_60d": 0.5458734820087806,
    "weight": 0.1552299410826021,
    "allocated_nav": 155.2299410826021
  },
  {
    "track": {
      "asset": "TRXUSDT",
      "timeframe": "1d",
      "venue": "spot",
      "mode": "long_only"
    },
    "ok": true,
    "as_of": "2026-06-12T23:59:59.999000+00:00",
    "current_close": 0.3152,
    "current_bar_high": 0.317,
    "current_bar_low": 0.3152,
    "current_atr_24h": 0.004986666382121708,
    "selected_strategy": "tsmom",
    "selected_params": {
      "lookback_h": 168
    },
    "param_label": "lb168h",
    "train_sharpe": 0.3379499241565231,
    "train_n_trades": 2,
    "train_in_market_pct": 0.9754098360655737,
    "stand_down": false,
    "raw_strategy_signal": 0,
    "current_signal": 0,
    "prior_signal": 0,
    "is_flip": false,
    "target_units": 0.0,
    "target_notional_sgd": 0.0,
    "stop_price": null,
    "stop_distance_pct": 3.1641284150518456,
    "prior_recommended_signal": 0,
    "first_run": false,
    "asset_realized_vol_60d": 0.23772135647320264,
    "weight": 0.3564505507957162,
    "allocated_nav": 356.4505507957162
  },
  {
    "track": {
      "asset": "RENDERUSDT",
      "timeframe": "1d",
      "venue": "spot",
      "mode": "long_only"
    },
    "ok": true,
    "as_of": "2026-06-12T23:59:59.999000+00:00",
    "current_close": 1.657,
    "current_bar_high": 1.669,
    "current_bar_low": 1.616,
    "current_atr_24h": 0.09821897716713977,
    "selected_strategy": "tsmom",
    "selected_params": {
      "lookback_h": 168
    },
    "param_label": "lb168h",
    "train_sharpe": 0.055544863720228016,
    "train_n_trades": 4,
    "train_in_market_pct": 0.912568306010929,
    "stand_down": true,
    "raw_strategy_signal": 0,
    "current_signal": 0,
    "prior_signal": 0,
    "is_flip": false,
    "target_units": 0.0,
    "target_notional_sgd": 0.0,
    "stop_price": null,
    "stop_distance_pct": 11.855036471592006,
    "prior_recommended_signal": 0,
    "first_run": false,
    "asset_realized_vol_60d": 0.7938752323745387,
    "weight": 0.10673706017673154,
    "allocated_nav": 106.73706017673155
  }
]