[
  {
    "track": {
      "asset": "BTCUSDT",
      "timeframe": "1d",
      "venue": "spot",
      "mode": "long_only"
    },
    "ok": true,
    "as_of": "2026-06-06T23:59:59.999000+00:00",
    "current_close": 59744.01,
    "current_bar_high": 61530.05,
    "current_bar_low": 59500.0,
    "current_atr_24h": 3097.796055694723,
    "selected_strategy": "macross",
    "selected_params": {
      "fast_h": 168,
      "slow_h": 720
    },
    "param_label": "f168h_s720h",
    "train_sharpe": -0.3911687559143654,
    "train_n_trades": 3,
    "train_in_market_pct": 0.644808743169399,
    "stand_down": true,
    "raw_strategy_signal": 0,
    "current_signal": 0,
    "prior_signal": 0,
    "is_flip": false,
    "target_units": 0.0,
    "target_notional_sgd": 0.0,
    "stop_price": null,
    "stop_distance_pct": 10.370231444774875,
    "prior_recommended_signal": 0,
    "first_run": false,
    "asset_realized_vol_60d": 0.38710343222548294,
    "weight": 0.2172048035098721,
    "allocated_nav": 217.20480350987208
  },
  {
    "track": {
      "asset": "ETHUSDT",
      "timeframe": "1d",
      "venue": "spot",
      "mode": "long_only"
    },
    "ok": true,
    "as_of": "2026-06-06T23:59:59.999000+00:00",
    "current_close": 1518.1,
    "current_bar_high": 1601.22,
    "current_bar_low": 1510.43,
    "current_atr_24h": 131.71708395204473,
    "selected_strategy": "tsmom",
    "selected_params": {
      "lookback_h": 720
    },
    "param_label": "lb720h",
    "train_sharpe": -0.12268735884930106,
    "train_n_trades": 2,
    "train_in_market_pct": 0.8114754098360656,
    "stand_down": true,
    "raw_strategy_signal": 0,
    "current_signal": 0,
    "prior_signal": 0,
    "is_flip": false,
    "target_units": 0.0,
    "target_notional_sgd": 0.0,
    "stop_price": null,
    "stop_distance_pct": 17.352886364803997,
    "prior_recommended_signal": 0,
    "first_run": false,
    "asset_realized_vol_60d": 0.5215762651547772,
    "weight": 0.16120504430849103,
    "allocated_nav": 161.20504430849104
  },
  {
    "track": {
      "asset": "SOLUSDT",
      "timeframe": "1d",
      "venue": "spot",
      "mode": "long_only"
    },
    "ok": true,
    "as_of": "2026-06-06T23:59:59.999000+00:00",
    "current_close": 60.49,
    "current_bar_high": 64.86,
    "current_bar_low": 60.36,
    "current_atr_24h": 5.477958274021159,
    "selected_strategy": "macross",
    "selected_params": {
      "fast_h": 168,
      "slow_h": 720
    },
    "param_label": "f168h_s720h",
    "train_sharpe": -0.34556800305333024,
    "train_n_trades": 3,
    "train_in_market_pct": 0.6475409836065574,
    "stand_down": true,
    "raw_strategy_signal": 0,
    "current_signal": 0,
    "prior_signal": 0,
    "is_flip": false,
    "target_units": 0.0,
    "target_notional_sgd": 0.0,
    "stop_price": null,
    "stop_distance_pct": 18.11194668216617,
    "prior_recommended_signal": 0,
    "first_run": false,
    "asset_realized_vol_60d": 0.5394486683213708,
    "weight": 0.15586418110210798,
    "allocated_nav": 155.86418110210798
  },
  {
    "track": {
      "asset": "TRXUSDT",
      "timeframe": "1d",
      "venue": "spot",
      "mode": "long_only"
    },
    "ok": true,
    "as_of": "2026-06-06T23:59:59.999000+00:00",
    "current_close": 0.3189,
    "current_bar_high": 0.3214,
    "current_bar_low": 0.3189,
    "current_atr_24h": 0.006696648455788531,
    "selected_strategy": "tsmom",
    "selected_params": {
      "lookback_h": 168
    },
    "param_label": "lb168h",
    "train_sharpe": 0.37979403446627735,
    "train_n_trades": 2,
    "train_in_market_pct": 0.9590163934426229,
    "stand_down": false,
    "raw_strategy_signal": 0,
    "current_signal": 0,
    "prior_signal": 0,
    "is_flip": false,
    "target_units": 0.0,
    "target_notional_sgd": 0.0,
    "stop_price": null,
    "stop_distance_pct": 4.19984224257669,
    "prior_recommended_signal": 0,
    "first_run": false,
    "asset_realized_vol_60d": 0.23323262699992509,
    "weight": 0.3605015559618086,
    "allocated_nav": 360.5015559618086
  },
  {
    "track": {
      "asset": "RENDERUSDT",
      "timeframe": "1d",
      "venue": "spot",
      "mode": "long_only"
    },
    "ok": true,
    "as_of": "2026-06-06T23:59:59.999000+00:00",
    "current_close": 1.561,
    "current_bar_high": 1.699,
    "current_bar_low": 1.558,
    "current_atr_24h": 0.23051453869694996,
    "selected_strategy": "tsmom",
    "selected_params": {
      "lookback_h": 168
    },
    "param_label": "lb168h",
    "train_sharpe": -0.02336288544263957,
    "train_n_trades": 4,
    "train_in_market_pct": 0.8961748633879781,
    "stand_down": true,
    "raw_strategy_signal": 0,
    "current_signal": 0,
    "prior_signal": 0,
    "is_flip": false,
    "target_units": 0.0,
    "target_notional_sgd": 0.0,
    "stop_price": null,
    "stop_distance_pct": 29.534213798456115,
    "prior_recommended_signal": 0,
    "first_run": false,
    "asset_realized_vol_60d": 0.7990609863734323,
    "weight": 0.10522441511772035,
    "allocated_nav": 105.22441511772035
  }
]