[
  {
    "track": {
      "asset": "BTCUSDT",
      "timeframe": "1d",
      "venue": "spot",
      "mode": "long_only"
    },
    "ok": true,
    "as_of": "2026-05-13T23:59:59.999000+00:00",
    "current_close": 81224.09,
    "current_bar_high": 81299.99,
    "current_bar_low": 80412.15,
    "current_atr_24h": 1390.8333760105963,
    "selected_strategy": "tsmom",
    "selected_params": {
      "lookback_h": 720
    },
    "param_label": "lb720h",
    "train_sharpe": -0.10109898150988492,
    "train_n_trades": 5,
    "train_in_market_pct": 0.6229508196721312,
    "stand_down": true,
    "raw_strategy_signal": 1,
    "current_signal": 0,
    "prior_signal": 1,
    "is_flip": false,
    "target_units": 0.0,
    "target_notional_sgd": 0.0,
    "stop_price": null,
    "stop_distance_pct": 3.4246819533726915,
    "prior_recommended_signal": 0,
    "first_run": false,
    "asset_realized_vol_60d": 0.3621609946159895,
    "weight": 0.2102812250515538,
    "allocated_nav": 210.2812250515538
  },
  {
    "track": {
      "asset": "ETHUSDT",
      "timeframe": "1d",
      "venue": "spot",
      "mode": "long_only"
    },
    "ok": true,
    "as_of": "2026-05-13T23:59:59.999000+00:00",
    "current_close": 2305.26,
    "current_bar_high": 2307.66,
    "current_bar_low": 2273.34,
    "current_atr_24h": 54.80858830621186,
    "selected_strategy": "tsmom",
    "selected_params": {
      "lookback_h": 720
    },
    "param_label": "lb720h",
    "train_sharpe": 0.06259784522812077,
    "train_n_trades": 3,
    "train_in_market_pct": 0.7759562841530054,
    "stand_down": true,
    "raw_strategy_signal": 0,
    "current_signal": 0,
    "prior_signal": 1,
    "is_flip": false,
    "target_units": 0.0,
    "target_notional_sgd": 0.0,
    "stop_price": null,
    "stop_distance_pct": 4.755089517556533,
    "prior_recommended_signal": 0,
    "first_run": false,
    "asset_realized_vol_60d": 0.5188036432296043,
    "weight": 0.14679090751881177,
    "allocated_nav": 146.79090751881176
  },
  {
    "track": {
      "asset": "SOLUSDT",
      "timeframe": "1d",
      "venue": "spot",
      "mode": "long_only"
    },
    "ok": true,
    "as_of": "2026-05-13T23:59:59.999000+00:00",
    "current_close": 95.65,
    "current_bar_high": 95.99,
    "current_bar_low": 94.05,
    "current_atr_24h": 2.9922401914737073,
    "selected_strategy": "meanrev",
    "selected_params": {
      "window_h": 336,
      "entry_z": 2.0,
      "exit_z": 0.0
    },
    "param_label": "w336h_z2.0_x0.0",
    "train_sharpe": 0.010681771692647953,
    "train_n_trades": 2,
    "train_in_market_pct": 0.8879781420765027,
    "stand_down": true,
    "raw_strategy_signal": 0,
    "current_signal": 0,
    "prior_signal": 0,
    "is_flip": false,
    "target_units": 0.0,
    "target_notional_sgd": 0.0,
    "stop_price": null,
    "stop_distance_pct": 12.513288829999821,
    "prior_recommended_signal": 0,
    "first_run": false,
    "asset_realized_vol_60d": 0.5119609068190851,
    "weight": 0.14875287663448697,
    "allocated_nav": 148.75287663448697
  },
  {
    "track": {
      "asset": "TRXUSDT",
      "timeframe": "1d",
      "venue": "spot",
      "mode": "long_only"
    },
    "ok": true,
    "as_of": "2026-05-13T23:59:59.999000+00:00",
    "current_close": 0.349,
    "current_bar_high": 0.3494,
    "current_bar_low": 0.3485,
    "current_atr_24h": 0.0025688306586868818,
    "selected_strategy": "tsmom",
    "selected_params": {
      "lookback_h": 336
    },
    "param_label": "lb336h",
    "train_sharpe": 0.7620422213616601,
    "train_n_trades": 2,
    "train_in_market_pct": 0.9590163934426229,
    "stand_down": false,
    "raw_strategy_signal": 1,
    "current_signal": 1,
    "prior_signal": 1,
    "is_flip": false,
    "target_units": 1108.7494231315127,
    "target_notional_sgd": 386.9535486728979,
    "stop_price": 0.3438623386826262,
    "stop_distance_pct": 1.4721092599924825,
    "prior_recommended_signal": 1,
    "first_run": false,
    "asset_realized_vol_60d": 0.19680826774925342,
    "weight": 0.3869535486728979,
    "allocated_nav": 386.9535486728979
  },
  {
    "track": {
      "asset": "RENDERUSDT",
      "timeframe": "1d",
      "venue": "spot",
      "mode": "long_only"
    },
    "ok": true,
    "as_of": "2026-05-13T23:59:59.999000+00:00",
    "current_close": 1.935,
    "current_bar_high": 1.944,
    "current_bar_low": 1.898,
    "current_atr_24h": 0.07535908817462995,
    "selected_strategy": "tsmom",
    "selected_params": {
      "lookback_h": 720
    },
    "param_label": "lb720h",
    "train_sharpe": 0.09819528588398124,
    "train_n_trades": 4,
    "train_in_market_pct": 0.5546448087431693,
    "stand_down": true,
    "raw_strategy_signal": 1,
    "current_signal": 0,
    "prior_signal": 1,
    "is_flip": false,
    "target_units": 0.0,
    "target_notional_sgd": 0.0,
    "stop_price": null,
    "stop_distance_pct": 7.789053041305421,
    "prior_recommended_signal": 0,
    "first_run": false,
    "asset_realized_vol_60d": 0.7102651867609641,
    "weight": 0.10722144212224953,
    "allocated_nav": 107.22144212224953
  }
]